bu_agent_sdk/__init__.py
bu_agent_sdk/observability.py
bu_agent_sdk/agent/README.md
bu_agent_sdk/agent/__init__.py
bu_agent_sdk/agent/events.py
bu_agent_sdk/agent/service.py
bu_agent_sdk/agent/compaction/__init__.py
bu_agent_sdk/agent/compaction/models.py
bu_agent_sdk/agent/compaction/service.py
bu_agent_sdk/examples/__init__.py
bu_agent_sdk/examples/claude_code.py
bu_agent_sdk/examples/dependency_injection.py
bu_agent_sdk/llm/README.md
bu_agent_sdk/llm/__init__.py
bu_agent_sdk/llm/base.py
bu_agent_sdk/llm/exceptions.py
bu_agent_sdk/llm/messages.py
bu_agent_sdk/llm/models.py
bu_agent_sdk/llm/schema.py
bu_agent_sdk/llm/views.py
bu_agent_sdk/llm/anthropic/chat.py
bu_agent_sdk/llm/anthropic/serializer.py
bu_agent_sdk/llm/google/__init__.py
bu_agent_sdk/llm/google/chat.py
bu_agent_sdk/llm/google/serializer.py
bu_agent_sdk/llm/google/tests/__init__.py
bu_agent_sdk/llm/google/tests/test_agent_mode.py
bu_agent_sdk/llm/openai/chat.py
bu_agent_sdk/llm/openai/like.py
bu_agent_sdk/llm/openai/serializer.py
bu_agent_sdk/tokens/__init__.py
bu_agent_sdk/tokens/custom_pricing.py
bu_agent_sdk/tokens/mappings.py
bu_agent_sdk/tokens/service.py
bu_agent_sdk/tokens/views.py
bu_agent_sdk/tools/__init__.py
bu_agent_sdk/tools/decorator.py
bu_agent_sdk/tools/depends.py
bu_agent_sdk-0.0.1.dist-info/METADATA
bu_agent_sdk-0.0.1.dist-info/WHEEL
bu_agent_sdk-0.0.1.dist-info/RECORD
