Metadata-Version: 2.4
Name: bu-agent-sdk
Version: 0.0.1
Summary: An agent is just a for-loop. The simplest possible agent framework.
Project-URL: Homepage, https://github.com/browser-use/bu-agent-sdk
Project-URL: Documentation, https://github.com/browser-use/bu-agent-sdk#readme
Project-URL: Repository, https://github.com/browser-use/bu-agent-sdk
Author-email: Browser Use <hello@browser-use.com>
License-Expression: MIT
Keywords: agent,ai,anthropic,google,llm,openai,tool-calling
Classifier: Development Status :: 3 - Alpha
Classifier: Intended Audience :: Developers
Classifier: License :: OSI Approved :: MIT License
Classifier: Programming Language :: Python :: 3
Classifier: Programming Language :: Python :: 3.11
Classifier: Programming Language :: Python :: 3.12
Classifier: Programming Language :: Python :: 3.13
Classifier: Topic :: Scientific/Engineering :: Artificial Intelligence
Requires-Python: >=3.11
Requires-Dist: aiohttp>=3.9.0
Requires-Dist: anthropic>=0.40.0
Requires-Dist: anyio>=4.12.1
Requires-Dist: dotenv>=0.9.9
Requires-Dist: google-genai>=1.0.0
Requires-Dist: httpx>=0.28.1
Requires-Dist: openai>=1.50.0
Requires-Dist: pydantic>=2.0.0
Provides-Extra: anthropic
Requires-Dist: anthropic>=0.40.0; extra == 'anthropic'
Provides-Extra: google
Requires-Dist: google-genai>=1.0.0; extra == 'google'
Provides-Extra: observability
Requires-Dist: lmnr>=0.4.0; extra == 'observability'
Provides-Extra: openai
Requires-Dist: openai>=1.50.0; extra == 'openai'
